bcos/__init__.py
bcos/common.py
bcos/settings.py
bcos/version.py
bcos/data/__init__.py
bcos/data/categories.py
bcos/data/datamodules.py
bcos/data/presets.py
bcos/data/sampler.py
bcos/data/transforms.py
bcos/data/caching/__init__.py
bcos/data/caching/shm_caching.py
bcos/data/caching/cached_imagefolder/__init__.py
bcos/data/caching/cached_imagefolder/cached_imagefolder.py
bcos/data/caching/cached_imagefolder/cached_loader.py
bcos/data/caching/cached_imagefolder/env.py
bcos/data/caching/cached_imagefolder/redis_store.py
bcos/data/caching/cached_imagefolder/store.py
bcos/experiments/CIFAR10/norm_ablations_final/experiment_parameters.py
bcos/experiments/CIFAR10/norm_ablations_final/model.py
bcos/experiments/ImageNet/baseline/experiment_parameters.py
bcos/experiments/ImageNet/baseline/model.py
bcos/experiments/ImageNet/bcos_final/experiment_parameters.py
bcos/experiments/ImageNet/bcos_final/model.py
bcos/experiments/ImageNet/bcos_final_long/experiment_parameters.py
bcos/experiments/ImageNet/bcos_final_long/model.py
bcos/experiments/ImageNet/vit_final/experiment_parameters.py
bcos/experiments/ImageNet/vit_final/model.py
bcos/experiments/utils/__init__.py
bcos/experiments/utils/config_utils.py
bcos/experiments/utils/exceptions.py
bcos/experiments/utils/structure_constants.py
bcos/experiments/utils/experiment_utils/__init__.py
bcos/experiments/utils/experiment_utils/experiment_utils.py
bcos/experiments/utils/experiment_utils/loading_utils.py
bcos/experiments/utils/experiment_utils/metric_utils.py
bcos/models/__init__.py
bcos/models/convnext.py
bcos/models/densenet.py
bcos/models/pretrained.py
bcos/models/resnet.py
bcos/models/vgg.py
bcos/models/vit.py
bcos/modules/__init__.py
bcos/modules/bcosconv2d.py
bcos/modules/bcoslinear.py
bcos/modules/common.py
bcos/modules/logitlayer.py
bcos/modules/losses.py
bcos/modules/norms/__init__.py
bcos/modules/norms/centered_norms.py
bcos/modules/norms/utils.py
bcos/modules/norms/uncentered_norms/__init__.py
bcos-0.1.3.dist-info/licenses/LICENSE
bcos-0.1.3.dist-info/METADATA
bcos-0.1.3.dist-info/WHEEL
bcos-0.1.3.dist-info/top_level.txt
bcos-0.1.3.dist-info/RECORD
