Metadata-Version: 2.4
Name: bcos
Version: 0.1.3
Summary: B-cos models.
Author-email: Moritz Böhle <mboehle@mpi-inf.mpg.de>, Navdeeppal Singh <npsingh0181@gmail.com>
License: Apache License 2.0
Project-URL: repository, https://github.com/B-cos/B-cos-v2/
License-File: LICENSE
Dynamic: license-file
